anisq/__init__.py
anisq/anisq.py
anisq-1.4.0.dist-info/METADATA
anisq-1.4.0.dist-info/WHEEL
anisq-1.4.0.dist-info/entry_points.txt
anisq-1.4.0.dist-info/top_level.txt
anisq-1.4.0.dist-info/RECORD
