Metadata-Version: 2.1
Name: anisq
Version: 1.4.0
Summary: Streaming / Downloading Albanian Subtitled Anime
Home-page: UNKNOWN
Author: deniscerri (Denis Çerri)
Author-email: 64997243+deniscerri@users.noreply.github.com
License: UNKNOWN
Keywords: python,video,stream,anime,albanian
Platform: UNKNOWN
Classifier: Development Status :: 5 - Production/Stable
Classifier: Intended Audience :: Developers
Classifier: Programming Language :: Python :: 3
Classifier: Operating System :: Unix
Classifier: Operating System :: MacOS :: MacOS X
Classifier: Operating System :: Microsoft :: Windows
Requires-Dist: bs4
Requires-Dist: cloudscraper
Requires-Dist: lxml
Requires-Dist: requests
